realDB/__init__.py
realDB/postgres.py
realDB/sqlite.py
realDB-0.2.2.dist-info/LICENSE
realDB-0.2.2.dist-info/METADATA
realDB-0.2.2.dist-info/WHEEL
realDB-0.2.2.dist-info/top_level.txt
realDB-0.2.2.dist-info/RECORD
