Metadata-Version: 2.1
Name: realDB
Version: 0.2.2
Summary: A unified python interface for different DB (e.g. sqlite, pg).
Home-page: https://e.coding.net/dataframe/real_py/PyPI_src_of_real.git
Author: Real He
Author-email: i874u@hotmail.com
License: BSD
Platform: UNKNOWN
Classifier: Development Status :: 4 - Beta
Classifier: Operating System :: OS Independent
Classifier: License :: OSI Approved :: BSD License
Classifier: Programming Language :: Python
Classifier: Programming Language :: Python :: 3
Classifier: Programming Language :: Python :: 3.6
Classifier: Programming Language :: Python :: 3.7
Classifier: Programming Language :: Python :: 3.8
Classifier: Programming Language :: Python :: 3.9
Classifier: Programming Language :: Python :: Implementation :: CPython
Requires-Python: >=3.6.0
Requires-Dist: psycopg2-binary
